peeweext/__init__.py
peeweext/fields.py
peeweext/flask.py
peeweext/mixins.py
peeweext/model.py
peeweext/otel.py
peeweext/sea.py
peeweext/validation.py
peeweext-1.2.8.dist-info/LICENSE
peeweext-1.2.8.dist-info/METADATA
peeweext-1.2.8.dist-info/WHEEL
peeweext-1.2.8.dist-info/top_level.txt
peeweext-1.2.8.dist-info/RECORD
