Metadata-Version: 2.1
Name: peeweext
Version: 1.2.8
Summary: peewee extension
Home-page: https://github.com/shanbay/peeweext
Author: Michael Ding
Author-email: yandy.ding@gmail.com
License: MIT
Keywords: peewee,orm
Classifier: Development Status :: 1 - Planning
Classifier: Environment :: Web Environment
Classifier: Intended Audience :: Developers
Classifier: Operating System :: POSIX
Classifier: License :: OSI Approved :: MIT License
Classifier: Programming Language :: Python
Classifier: Programming Language :: Python :: 3
Classifier: Programming Language :: Python :: 3.4
Classifier: Programming Language :: Python :: 3.5
Classifier: Programming Language :: Python :: 3.6
Classifier: Topic :: Internet
Classifier: Topic :: Software Development :: Libraries :: Python Modules
Requires-Python: >=3
License-File: LICENSE
Requires-Dist: peewee
Requires-Dist: pendulum >=2.0.0
Requires-Dist: blinker
Requires-Dist: opentelemetry-instrumentation-pymysql
Requires-Dist: opentelemetry-instrumentation-mysqlclient
